navertrans/__init__.py
navertrans/constants.py
navertrans/navertrans.py
navertrans/response.py
navertrans-0.1.1.dist-info/LICENSE
navertrans-0.1.1.dist-info/METADATA
navertrans-0.1.1.dist-info/WHEEL
navertrans-0.1.1.dist-info/top_level.txt
navertrans-0.1.1.dist-info/RECORD
